easymockups/__init__.py
easymockups/apps.py
easymockups/models.py
easymockups/tests.py
easymockups/urls.py
easymockups/views.py
easy_django_mockups-0.1.1.dist-info/LICENSE
easy_django_mockups-0.1.1.dist-info/METADATA
easy_django_mockups-0.1.1.dist-info/WHEEL
easy_django_mockups-0.1.1.dist-info/top_level.txt
easy_django_mockups-0.1.1.dist-info/RECORD
