Metadata-Version: 2.1
Name: easy-django-mockups
Version: 0.1.1
Summary: A simple Django app to allow for quick protyping of templates without a need for a corresponding Django View.
Home-page: https://www.example.com/
Author: Industry Dive
Author-email: tech.team@industrydive.com
License: BSD License
Platform: UNKNOWN
Classifier: Environment :: Web Environment
Classifier: Framework :: Django
Classifier: Framework :: Django :: 1.11
Classifier: Intended Audience :: Developers
Classifier: License :: OSI Approved :: BSD License
Classifier: Operating System :: OS Independent
Classifier: Programming Language :: Python
Classifier: Programming Language :: Python :: 2.7
Classifier: Topic :: Internet :: WWW/HTTP
Classifier: Topic :: Internet :: WWW/HTTP :: Dynamic Content
